AUTHORS.rst
CONTRIBUTING.rst
HISTORY.rst
LICENSE
MANIFEST.in
README.rst
setup.cfg
setup.py
docs/Makefile
docs/make.bat
docs/build/html/_static/file.png
docs/build/html/_static/logo.jpg
docs/build/html/_static/logo2.png
docs/build/html/_static/minus.png
docs/build/html/_static/plus.png
docs/source/authors.rst
docs/source/conf.py
docs/source/contributing.rst
docs/source/history.rst
docs/source/index.rst
docs/source/installation.rst
docs/source/modules.rst
docs/source/persistence.rst
docs/source/readme.rst
docs/source/todo.rst
docs/source/usage.rst
docs/source/_static/logo.jpg
docs/source/_static/logo2.png
docs/source/session/session.rst
docs/source/synchronization/synchronization.rst
gutools/__init__.py
gutools/bash_completer.py
gutools/cli.py
gutools/colors.py
gutools/loggers.py
gutools/persistence.py
gutools/recording.py
gutools/session.py
gutools/stm.py
gutools/system.py
gutools/tools.py
gutools/uagents.py
gutools/uapplication.py
gutools/ulogging.py
gutools/unet.py
gutools/uobjects.py
gutools/upytest.py
gutools/ushift.py
gutools/utests.py
gutools/uworkspace.py
gutools.egg-info/PKG-INFO
gutools.egg-info/SOURCES.txt
gutools.egg-info/dependency_links.txt
gutools.egg-info/entry_points.txt
gutools.egg-info/not-zip-safe
gutools.egg-info/requires.txt
gutools.egg-info/top_level.txt
tests/.coverage
tests/__init__.py
tests/application.log
tests/coverage.xml
tests/errors.log
tests/info.log
tests/reactor.dot
tests/reactor.dot.svg
tests/report.xml
tests/stm.log
tests/system.log
tests/test_loop.py
tests/test_session.py
tests/test_stm.py
tests/test_unet.py
tests/test_utools.py
tests/htmlcov/__init___py.html
tests/htmlcov/_home_agp_Documents_me_code_gutools_gutools___init___py.html
tests/htmlcov/_home_agp_Documents_me_code_gutools_gutools_bash_completer_py.html
tests/htmlcov/_home_agp_Documents_me_code_gutools_gutools_cli_py.html
tests/htmlcov/_home_agp_Documents_me_code_gutools_gutools_colors_py.html
tests/htmlcov/_home_agp_Documents_me_code_gutools_gutools_controllers___init___py.html
tests/htmlcov/_home_agp_Documents_me_code_gutools_gutools_controllers_arguments_py.html
tests/htmlcov/_home_agp_Documents_me_code_gutools_gutools_controllers_session_py.html
