Metadata-Version: 1.1
Name: gutools
Version: 0.1.7
Summary: Univeral Tools for programing
Home-page: https://github.com/asteriogonzalez/gutools
Author: Asterio
Author-email: asterio.gonzalez@gmail.com
License: MIT license
Keywords: gutools
Platform: UNKNOWN
Classifier: Development Status :: 2 - Pre-Alpha
Classifier: Intended Audience :: Developers
Classifier: License :: OSI Approved :: MIT License
Classifier: Natural Language :: English
Classifier: Programming Language :: Python :: 3.5
Classifier: Programming Language :: Python :: 3.6
Classifier: Programming Language :: Python :: 3.7
